desdeo/__init__.py
desdeo/api/README.md
desdeo/api/__init__.py
desdeo/api/app.py
desdeo/api/config.py
desdeo/api/config.toml
desdeo/api/db.py
desdeo/api/db_init.py
desdeo/api/db_models.py
desdeo/api/malaga_db_init.py
desdeo/api/models/__init__.py
desdeo/api/models/archive.py
desdeo/api/models/preference.py
desdeo/api/models/problem.py
desdeo/api/models/reference_point_method.py
desdeo/api/models/session.py
desdeo/api/models/state.py
desdeo/api/models/user.py
desdeo/api/routers/_NAUTILUS.py
desdeo/api/routers/_NAUTILUS_navigator.py
desdeo/api/routers/_NIMBUS.py
desdeo/api/routers/__init__.py
desdeo/api/routers/problem.py
desdeo/api/routers/reference_point_method.py
desdeo/api/routers/session.py
desdeo/api/routers/test.py
desdeo/api/routers/user_authentication.py
desdeo/api/schema.py
desdeo/api/tests/__init__.py
desdeo/api/tests/conftest.py
desdeo/api/tests/test_models.py
desdeo/api/tests/test_routes.py
desdeo/api/utils/database.py
desdeo/api/utils/logger.py
desdeo/core.py
desdeo/emo/__init__.py
desdeo/emo/hooks/archivers.py
desdeo/emo/methods/EAs.py
desdeo/emo/methods/__init__.py
desdeo/emo/methods/bases.py
desdeo/emo/operators/__init__.py
desdeo/emo/operators/crossover.py
desdeo/emo/operators/evaluator.py
desdeo/emo/operators/generator.py
desdeo/emo/operators/mutation.py
desdeo/emo/operators/selection.py
desdeo/emo/operators/termination.py
desdeo/explanations/__init__.py
desdeo/explanations/explainer.py
desdeo/explanations/utils.py
desdeo/mcdm/__init__.py
desdeo/mcdm/nautili.py
desdeo/mcdm/nautilus.py
desdeo/mcdm/nautilus_navigator.py
desdeo/mcdm/nimbus.py
desdeo/mcdm/pareto_navigator.py
desdeo/mcdm/reference_point_method.py
desdeo/problem/__init__.py
desdeo/problem/evaluator.py
desdeo/problem/gurobipy_evaluator.py
desdeo/problem/infix_parser.py
desdeo/problem/json_parser.py
desdeo/problem/pyomo_evaluator.py
desdeo/problem/schema.py
desdeo/problem/simulator_evaluator.py
desdeo/problem/sympy_evaluator.py
desdeo/problem/testproblems/__init__.py
desdeo-2.0.0.dist-info/LICENSE
desdeo-2.0.0.dist-info/METADATA
desdeo-2.0.0.dist-info/WHEEL
desdeo-2.0.0.dist-info/RECORD
