Metadata-Version: 2.3
Name: desdeo
Version: 2.0.0
Summary: DESDEO is a modular and open source framework for interactive multiobjective optimization.
License: MIT
Author: Giovanni Misitano
Author-email: giovanni.a.misitano@jyu.fi
Requires-Python: >=3.12,<3.13
Classifier: License :: OSI Approved :: MIT License
Classifier: Programming Language :: Python :: 3
Classifier: Programming Language :: Python :: 3.12
Requires-Dist: bayesian-optimization (>=1.0,<2.0)
Requires-Dist: cvxpy[scip] (>=1.6.4,<2.0.0)
Requires-Dist: greenlet (>=3.1.1,<4.0.0)
Requires-Dist: gurobipy (>=12.0.0,<13.0.0)
Requires-Dist: nevergrad (>=1.0.12,<2.0.0)
Requires-Dist: numba (>=0.61.0,<0.62.0)
Requires-Dist: numpy (>=2.2.0,<3.0.0)
Requires-Dist: polars (>=1.17,<2.0)
Requires-Dist: pyarrow (>=20.0.0,<21.0.0)
Requires-Dist: pydantic (>=2.9,<3.0)
Requires-Dist: pymoo (>=0.6.1.2,<0.7.0.0)
Requires-Dist: pyomo (>=6.8,<7.0)
Requires-Dist: pyparsing (>=3.0,<4.0)
Requires-Dist: scipy (>=1.11.4,<2.0.0)
Requires-Dist: shap (>=0.47.0,<0.48.0)
Requires-Dist: sympy (>=1.0,<2.0)
Requires-Dist: tsp-solver (>=0.1,<0.2)
